pysss/__init__.py
pysss/pysss.py
pysss-1.0.0.dist-info/LICENSE
pysss-1.0.0.dist-info/METADATA
pysss-1.0.0.dist-info/WHEEL
pysss-1.0.0.dist-info/top_level.txt
pysss-1.0.0.dist-info/RECORD
