Metadata-Version: 2.1
Name: pysss
Version: 1.0.0
Summary: Shamir's secret sharing algorithm in Python
Home-page: https://github.com/mohamed/pysss
Author: Mohamed A. Bamakhrama
Author-email: mohamed@alumni.tum.de
License: UNKNOWN
Project-URL: Bug Tracker, https://github.com/mohamed/pysss/issues
Platform: UNKNOWN
Classifier: Programming Language :: Python :: 3
Classifier: License :: OSI Approved :: BSD License
Classifier: Operating System :: OS Independent
Requires-Python: >=3.6
License-File: LICENSE
